buvis/pybase/__init__.py
buvis/pybase/adapters/__init__.py
buvis/pybase/adapters/console/__init__.py
buvis/pybase/adapters/console/capturing_rich_handler.py
buvis/pybase/adapters/console/console.py
buvis/pybase/adapters/jira/__init__.py
buvis/pybase/adapters/jira/jira.py
buvis/pybase/adapters/jira/domain/__init__.py
buvis/pybase/adapters/jira/domain/jira_issue_dto.py
buvis/pybase/adapters/outlook_local/__init__.py
buvis/pybase/adapters/outlook_local/exceptions.py
buvis/pybase/adapters/outlook_local/outlook_local.py
buvis/pybase/adapters/shell/__init__.py
buvis/pybase/adapters/shell/shell.py
buvis/pybase/adapters/uv/__init__.py
buvis/pybase/adapters/uv/uv.py
buvis/pybase/adapters/uv/uv_tool.py
buvis/pybase/command/__init__.py
buvis/pybase/command/command.py
buvis/pybase/configuration/__init__.py
buvis/pybase/configuration/click_integration.py
buvis/pybase/configuration/exceptions.py
buvis/pybase/configuration/loader.py
buvis/pybase/configuration/resolver.py
buvis/pybase/configuration/settings.py
buvis/pybase/configuration/source.py
buvis/pybase/configuration/validators.py
buvis/pybase/configuration/examples/__init__.py
buvis/pybase/configuration/examples/music_settings.py
buvis/pybase/configuration/examples/photo_settings.py
buvis/pybase/filesystem/__init__.py
buvis/pybase/filesystem/dir_tree/delete_by_extension.py
buvis/pybase/filesystem/dir_tree/dir_tree.py
buvis/pybase/filesystem/dir_tree/lowercase_file_extensions.py
buvis/pybase/filesystem/dir_tree/merge_mac_metadata.py
buvis/pybase/filesystem/dir_tree/remove_empty_directories.py
buvis/pybase/filesystem/dir_tree/rename_equivalent_extensions.py
buvis/pybase/filesystem/dir_tree/safe_rglob.py
buvis/pybase/filesystem/file_metadata/file_metadata_reader.py
buvis/pybase/formatting/__init__.py
buvis/pybase/formatting/string_operator/__init__.py
buvis/pybase/formatting/string_operator/abbr.py
buvis/pybase/formatting/string_operator/string_case_tools.py
buvis/pybase/formatting/string_operator/string_operator.py
buvis_pybase-0.9.0.dist-info/METADATA
buvis_pybase-0.9.0.dist-info/WHEEL
buvis_pybase-0.9.0.dist-info/licenses/LICENSE
buvis_pybase-0.9.0.dist-info/RECORD
